{
  "version": "0.6.0",
  "last_updated": "2026-06-26",
  "session": "session-006",
  "total_entries": 24,
  "total_categories": 7,
  "total_subcategories": 21,
  "total_sources": 55,
  "total_claims": 70,
  "total_comparisons": 7,
  "classification_summary": {
    "practical": 17,
    "emerging": 4,
    "theoretical": 3,
    "rejected": 0,
    "pending": 0
  },
  "proof_score_summary": {
    "4_stars": 8,
    "3_stars": 12,
    "2_stars": 4,
    "1_star": 0
  },
  "playbooks_count": 5,
  "comparisons_count": 7,
  "glossary_terms": 62,
  "taxonomy_version": "2.0"
}